hfunctions/__init__.py
hfunctions/_hfunctions.py
hfunctions/cli.py
hfunctions-0.1.1.dist-info/AUTHORS.rst
hfunctions-0.1.1.dist-info/LICENSE
hfunctions-0.1.1.dist-info/METADATA
hfunctions-0.1.1.dist-info/WHEEL
hfunctions-0.1.1.dist-info/entry_points.txt
hfunctions-0.1.1.dist-info/top_level.txt
hfunctions-0.1.1.dist-info/RECORD
