Metadata-Version: 2.1
Name: hfunctions
Version: 0.1.1
Summary: Handy function for data science work
Home-page: https://github.com/ahmedsalhin/hfunctions
Author: Ahmed Salhin
Author-email: ahmed@salhin.org
License: MIT license
Keywords: hfunctions
Platform: UNKNOWN
Classifier: Development Status :: 2 - Pre-Alpha
Classifier: Intended Audience :: Developers
Classifier: License :: OSI Approved :: MIT License
Classifier: Natural Language :: English
Classifier: Programming Language :: Python :: 3
Classifier: Programming Language :: Python :: 3.5
Classifier: Programming Language :: Python :: 3.6
Classifier: Programming Language :: Python :: 3.7
Classifier: Programming Language :: Python :: 3.8
Requires-Python: >=3.5
Requires-Dist: Click (>=7.0)
